hfhvar/__init__.py
hfhvar/bootstrap.py
hfhvar/cli.py
hfhvar/config.py
hfhvar/estimation.py
hfhvar/identification.py
hfhvar/io.py
hfhvar/plotting.py
hfhvar/simulation.py
hfhvar-0.1.1.dist-info/licenses/LICENSE
hfhvar-0.1.1.dist-info/METADATA
hfhvar-0.1.1.dist-info/WHEEL
hfhvar-0.1.1.dist-info/entry_points.txt
hfhvar-0.1.1.dist-info/top_level.txt
hfhvar-0.1.1.dist-info/RECORD
